LICENSE
README.md
pyproject.toml
setup.py
tactigon_arduino_braccio/__init__.py
tactigon_arduino_braccio/models.py
tactigon_arduino_braccio.egg-info/PKG-INFO
tactigon_arduino_braccio.egg-info/SOURCES.txt
tactigon_arduino_braccio.egg-info/dependency_links.txt
tactigon_arduino_braccio.egg-info/requires.txt
tactigon_arduino_braccio.egg-info/top_level.txt
tactigon_arduino_braccio/middleware/__init__.py
tactigon_arduino_braccio/middleware/solver.py